thread_worker/__init__.py
thread_worker/asyncWorker.py
thread_worker-0.1.10.dist-info/LICENSE.txt
thread_worker-0.1.10.dist-info/METADATA
thread_worker-0.1.10.dist-info/WHEEL
thread_worker-0.1.10.dist-info/top_level.txt
thread_worker-0.1.10.dist-info/RECORD
