Metadata-Version: 2.1
Name: thread-worker
Version: 0.1.10
Summary: thread work
Home-page: https://github.com/Ciyfly/thread_work
Author: recar
Author-email: recar@recar.com
License: UNKNOWN
Platform: UNKNOWN
License-File: LICENSE.txt
